[{
	"cardBackId": "0",
	"name": "Klassisch",
	"description": "Der Kartenr\u00fccken schlechthin.",
	"source": "startup",
	"sourceDescription": "Standard",
	"enabled": true,
	"img": "http://wow.zamimg.com/images/hearthstone/backs/original/Card_Back_Default.png",
	"imgAnimated": "http://wow.zamimg.com/images/hearthstone/backs/animated/Card_Back_Default.gif",
	"sortCategory": "1",
	"sortOrder": "1",
	"locale": "deDE"
},
{
	"cardBackId": "1",
	"name": "Pandaria",
	"description": "Hearthstone ist in Pandaria total beliebt. Die Shado-Pan haben es sogar zu ihrem offiziellen Kartenspiel ernannt!",
	"source": "season",
	"sourceDescription": "Saison",
	"howToGet": "Belohnung f\u00fcr alle Spieler, die im April 2014 im gewerteten Modus Rang 20 erreicht haben.",
	"enabled": true,
	"img": "http://wow.zamimg.com/images/hearthstone/backs/original/Card_Back_Pandaria.png",
	"imgAnimated": "http://wow.zamimg.com/images/hearthstone/backs/animated/Card_Back_Pandaria.gif",
	"sortCategory": "5",
	"sortOrder": "0",
	"locale": "deDE"
},
{
	"cardBackId": "2",
	"name": "Der Schwarze Tempel",
	"description": "Teufelsgr\u00fcn ist im Schwarzen Tempel immer in.",
	"source": "season",
	"sourceDescription": "Saison",
	"howToGet": "Belohnung f\u00fcr alle Spieler, die im Mai 2014 im gewerteten Modus Rang 20 erreicht haben.",
	"enabled": true,
	"img": "http://wow.zamimg.com/images/hearthstone/backs/original/Card_Back_BlackTemple.png",
	"imgAnimated": "http://wow.zamimg.com/images/hearthstone/backs/animated/Card_Back_BlackTemple.gif",
	"sortCategory": "5",
	"sortOrder": "0",
	"locale": "deDE"
},
{
	"cardBackId": "3",
	"name": "Regenbogen",
	"description": "Ja, der Regenbogengenerator kann leider nur ovale Regenbogen generieren. Gnomische Technologie ...",
	"source": "season",
	"sourceDescription": "Saison",
	"howToGet": "Belohnung f\u00fcr alle Spieler, die im Juni 2014 im gewerteten Modus Rang 20 erreicht haben.",
	"enabled": true,
	"img": "http://wow.zamimg.com/images/hearthstone/backs/original/Card_Back_Charm.png",
	"imgAnimated": "http://wow.zamimg.com/images/hearthstone/backs/animated/Card_Back_Charm.gif",
	"sortCategory": "5",
	"sortOrder": "0",
	"locale": "deDE"
},
{
	"cardBackId": "4",
	"name": "Stammtischfreunde",
	"description": "Ein nettes Geschenk vom Gastwirt. Er liebt es, wenn seine G\u00e4ste gemeinsam Spa\u00df haben!",
	"source": "achieve",
	"sourceDescription": "Promo",
	"howToGet": "Belohnung f\u00fcr 3 bestrittene Partien gegen Spieler auf dem gleichen lokalen Netzwerk (mind. 3 Spieler m\u00fcssen auf dem Netzwerk sein).",
	"enabled": true,
	"img": "http://wow.zamimg.com/images/hearthstone/backs/original/Card_Back_Launch.png",
	"imgAnimated": "http://wow.zamimg.com/images/hearthstone/backs/animated/Card_Back_Launch.gif",
	"sortCategory": "2",
	"sortOrder": "1",
	"locale": "deDE"
},
{
	"cardBackId": "5",
	"name": "Legende",
	"description": "Wow. Hardcore.",
	"source": "achieve",
	"sourceDescription": "Legende",
	"howToGet": "Belohnung f\u00fcr Spieler, die im gewerteten Modus den Rang \u201eLegende\u201c erreicht haben.",
	"enabled": true,
	"img": "http://wow.zamimg.com/images/hearthstone/backs/original/Card_Back_Legend.png",
	"imgAnimated": "http://wow.zamimg.com/images/hearthstone/backs/animated/Card_Back_Legend.gif",
	"sortCategory": "6",
	"sortOrder": "1",
	"locale": "deDE"
},
{
	"cardBackId": "6",
	"name": "Naxxramas",
	"description": "Glibberiger gr\u00fcner Schleim ... Da kommen Erinnerungen hoch. Bitte nicht abschlecken.",
	"source": "season",
	"sourceDescription": "Saison",
	"howToGet": "Belohnung f\u00fcr alle Spieler, die im Juli 2014 im gewerteten Modus Rang 20 erreicht haben.",
	"enabled": true,
	"img": "http://wow.zamimg.com/images/hearthstone/backs/original/Card_Back_Naxxramas.png",
	"imgAnimated": "http://wow.zamimg.com/images/hearthstone/backs/animated/Card_Back_Naxxramas.gif",
	"sortCategory": "5",
	"sortOrder": "0",
	"locale": "deDE"
},
{
	"cardBackId": "7",
	"name": "Naxxramas (Heroisch)",
	"description": "Dieser Kartenr\u00fccken platzt wortw\u00f6rtlich aus allen N\u00e4hten.",
	"source": "fixed_reward",
	"sourceDescription": "Abenteuer",
	"howToGet": "Belohnung f\u00fcr Spieler, die den Fluch von Naxxramas im heroischen Modus abgeschlossen haben.",
	"enabled": true,
	"img": "http://wow.zamimg.com/images/hearthstone/backs/original/Card_Back_Naxxramas2.png",
	"imgAnimated": "http://wow.zamimg.com/images/hearthstone/backs/animated/Card_Back_Naxxramas2.gif",
	"sortCategory": "3",
	"sortOrder": "1",
	"locale": "deDE"
},
{
	"cardBackId": "8",
	"name": "Eiskrone",
	"description": "Im gefrorenen Herzen der Eiskronenzitadelle wird jeder Held auf die Probe gestellt. Zieht Euch warm an.",
	"source": "season",
	"sourceDescription": "Saison",
	"howToGet": "Belohnung f\u00fcr alle Spieler, die im August 2014 im gewerteten Modus Rang 20 erreicht haben.",
	"enabled": true,
	"img": "http://wow.zamimg.com/images/hearthstone/backs/original/Card_Back_IceCrown.png",
	"imgAnimated": "http://wow.zamimg.com/images/hearthstone/backs/animated/Card_Back_IceCrown.gif",
	"sortCategory": "5",
	"sortOrder": "0",
	"locale": "deDE"
},
{
	"cardBackId": "9",
	"name": "Piraten!",
	"description": "Sch\u00e4tze, Papageien und \u2018ne Buddel voll Rum. So viel besser als Ninjas!",
	"source": "season",
	"sourceDescription": "Saison",
	"howToGet": "Belohnung f\u00fcr alle Spieler, die im September 2014 im gewerteten Modus Rang 20 erreicht haben.",
	"enabled": true,
	"img": "http://wow.zamimg.com/images/hearthstone/backs/original/Card_Back_Pirate.png",
	"imgAnimated": "http://wow.zamimg.com/images/hearthstone/backs/animated/Card_Back_Pirate.gif",
	"sortCategory": "5",
	"sortOrder": "0",
	"locale": "deDE"
},
{
	"cardBackId": "10",
	"name": "Schlottern\u00e4chte",
	"description": "S\u00fc\u00dfes oder Saures! Werdet Ihr einen leckeren Lutscher erwischen oder den Ersatzkopf des kopflosen Reiters?",
	"source": "season",
	"sourceDescription": "Saison",
	"howToGet": "Belohnung f\u00fcr alle Spieler, die im Oktober 2014 im gewerteten Modus Rang 20 erreicht haben.",
	"enabled": true,
	"img": "http://wow.zamimg.com/images/hearthstone/backs/original/Card_Back_Hallows_End.png",
	"imgAnimated": "http://wow.zamimg.com/images/hearthstone/backs/animated/Card_Back_Hallows_End.gif",
	"sortCategory": "5",
	"sortOrder": "0",
	"locale": "deDE"
},
{
	"cardBackId": "11",
	"name": "Goblins",
	"description": "Vier von f\u00fcnf Goblins best\u00e4tigen, dass dieser Kartenr\u00fccken explosionsfest ist!",
	"source": "season",
	"sourceDescription": "Saison",
	"howToGet": "Belohnung f\u00fcr alle Spieler, die im November 2014 im gewerteten Modus Rang 20 erreicht haben.",
	"enabled": true,
	"img": "http://wow.zamimg.com/images/hearthstone/backs/original/Card_Back_Goblin.png",
	"imgAnimated": "http://wow.zamimg.com/images/hearthstone/backs/animated/Card_Back_Goblin.gif",
	"sortCategory": "5",
	"sortOrder": "0",
	"locale": "deDE"
},
{
	"cardBackId": "12",
	"name": "Blizzard 2014",
	"description": "Hearthstones erstes Jahr. Und was f\u00fcr eines!",
	"source": "achieve",
	"sourceDescription": "Promo",
	"howToGet": "Belohnung f\u00fcr Spieler, die 2014 an Blizzard-Events teilgenommen haben.",
	"enabled": true,
	"img": "http://wow.zamimg.com/images/hearthstone/backs/original/Card_Back_Blizzard2014.png",
	"imgAnimated": "http://wow.zamimg.com/images/hearthstone/backs/animated/Card_Back_Blizzard2014.gif",
	"sortCategory": "11",
	"sortOrder": "1",
	"locale": "deDE"
},
{
	"cardBackId": "13",
	"name": "Die Flamme Dalarans",
	"description": "Das Maskottchen der Universit\u00e4t von Dalaran. Nur sehr selten zu sehen, weil niemand je zu den Rugbyspielen auftaucht.",
	"source": "achieve",
	"sourceDescription": "Promo",
	"howToGet": "Belohnung f\u00fcr Mitglieder von TeSPA oder einem anderen Uni-Partnerprogramm.",
	"enabled": true,
	"img": "http://wow.zamimg.com/images/hearthstone/backs/original/Card_Back_TeSPA.png",
	"imgAnimated": "http://wow.zamimg.com/images/hearthstone/backs/animated/Card_Back_TeSPA.gif",
	"sortCategory": "7",
	"sortOrder": "1",
	"locale": "deDE"
},
{
	"cardBackId": "14",
	"name": "Warlords",
	"description": "Wenn sie nicht gerade versucht, die Weltherrschaft an sich zu rei\u00dfen, spielt sogar die Eiserne Horde gerne mal eine Partie Hearthstone.",
	"source": "achieve",
	"sourceDescription": "Promo",
	"howToGet": "Belohnung f\u00fcr Spieler, die die Digital Deluxe Edition von Warlords of Draenor besitzen.",
	"enabled": true,
	"img": "http://wow.zamimg.com/images/hearthstone/backs/original/Card_Back_Warlords_of_Draenor.png",
	"imgAnimated": "http://wow.zamimg.com/images/hearthstone/backs/animated/Card_Back_Warlords_of_Draenor.gif",
	"sortCategory": "8",
	"sortOrder": "2",
	"locale": "deDE"
},
{
	"cardBackId": "15",
	"name": "Gnome",
	"description": "Multifunktionaler Kartenr\u00fccken, der auch als gnomisches Armeemesser, Schuhl\u00f6ffel oder Tiefenbahnticket einsetzbar ist.",
	"source": "season",
	"sourceDescription": "Saison",
	"howToGet": "Belohnung f\u00fcr alle Spieler, die im Dezember 2014 im gewerteten Modus Rang 20 erreicht haben.",
	"enabled": true,
	"img": "http://wow.zamimg.com/images/hearthstone/backs/original/Card_Back_Gnome.png",
	"imgAnimated": "http://wow.zamimg.com/images/hearthstone/backs/animated/Card_Back_Gnome.gif",
	"sortCategory": "5",
	"sortOrder": "0",
	"locale": "deDE"
},
{
	"cardBackId": "16",
	"name": "Maraad",
	"description": "Verteidiger Maraad war ein \u00e4u\u00dferst k\u00fchner und starker Paladin. Lasst Euch von den sch\u00f6nen Pastellt\u00f6nen nicht beeindrucken.",
	"source": "season",
	"sourceDescription": "Saison",
	"howToGet": "Belohnung f\u00fcr alle Spieler, die im Januar 2015 im gewerteten Modus Rang 20 erreicht haben.",
	"enabled": true,
	"img": "http://wow.zamimg.com/images/hearthstone/backs/original/Card_Back_Maraad.png",
	"imgAnimated": "http://wow.zamimg.com/images/hearthstone/backs/animated/Card_Back_Maraad.gif",
	"sortCategory": "5",
	"sortOrder": "0",
	"locale": "deDE"
},
{
	"cardBackId": "17",
	"name": "Mondfest",
	"description": "Frohes Mondfest!",
	"source": "season",
	"sourceDescription": "Saison",
	"howToGet": "Belohnung f\u00fcr alle Spieler, die im Februar 2015 im gewerteten Modus Rang 20 erreicht haben.",
	"enabled": true,
	"img": "http://wow.zamimg.com/images/hearthstone/backs/original/Card_Back_Lunar.png",
	"imgAnimated": "http://wow.zamimg.com/images/hearthstone/backs/animated/Card_Back_Lunar.gif",
	"sortCategory": "5",
	"sortOrder": "0",
	"locale": "deDE"
},
{
	"cardBackId": "18",
	"name": "Geschmolzener Kern",
	"description": "Der Geschmolzene Kern des Schwarzfels, nicht die Mitte eines leckeren Schokoladekuchens. Leider.",
	"source": "achieve",
	"sourceDescription": "Promo",
	"howToGet": "Belohnung f\u00fcr Spieler, die den Schwarzfels im Vorverkauf erworben haben.",
	"enabled": true,
	"img": "http://wow.zamimg.com/images/hearthstone/backs/original/Card_Back_MoltonCore.png",
	"imgAnimated": "http://wow.zamimg.com/images/hearthstone/backs/animated/Card_Back_MoltonCore.gif",
	"sortCategory": "10",
	"sortOrder": "1",
	"locale": "deDE"
},
{
	"cardBackId": "19",
	"name": "Ragnaros",
	"description": "Der Feuerf\u00fcrst entspannt sich meist gem\u00fctlich im Lavapool \u2013 auch bei dem Versuch, die Welt niederzubrennen.",
	"source": "season",
	"sourceDescription": "Saison",
	"howToGet": "Belohnung f\u00fcr alle Spieler, die im M\u00e4rz 2015 im gewerteten Modus Rang 20 erreicht haben.",
	"enabled": true,
	"img": "http://wow.zamimg.com/images/hearthstone/backs/original/Card_Back_Ragnaros.png",
	"imgAnimated": "http://wow.zamimg.com/images/hearthstone/backs/animated/Card_Back_Ragnaros.gif",
	"sortCategory": "5",
	"sortOrder": "0",
	"locale": "deDE"
},
{
	"cardBackId": "20",
	"name": "Goldenes Fest",
	"description": "Echtes Gold, Baby.",
	"source": "achieve",
	"sourceDescription": "Promo",
	"howToGet": "Belohnung f\u00fcr Spieler, die bei ausgew\u00e4hlten eSports-Events sehr gut abgeschnitten haben.",
	"enabled": true,
	"img": "http://wow.zamimg.com/images/hearthstone/backs/original/Card_Back_GoldenCelebration.png",
	"imgAnimated": "http://wow.zamimg.com/images/hearthstone/backs/animated/Card_Back_GoldenCelebration.gif",
	"sortCategory": "12",
	"sortOrder": "1",
	"locale": "deDE"
},
{
	"cardBackId": "21",
	"name": "Nefarian",
	"description": "Es ist kaum zu glauben, dass Ihr ihm tats\u00e4chlich \u00fcber den Weg getraut habt. War denn der Bart nicht Hinweis genug?",
	"source": "fixed_reward",
	"sourceDescription": "Abenteuer",
	"howToGet": "Belohnung f\u00fcr Spieler, die den Schwarzfels im heroischen Modus abgeschlossen haben.",
	"enabled": true,
	"img": "http://wow.zamimg.com/images/hearthstone/backs/original/Card_Back_Nefarian.png",
	"imgAnimated": "http://wow.zamimg.com/images/hearthstone/backs/animated/Card_Back_Nefarian.gif",
	"sortCategory": "3",
	"sortOrder": "2",
	"locale": "deDE"
},
{
	"cardBackId": "22",
	"name": "Cupcake",
	"description": "Ihr wollt wissen, ob das ein Cupcake auf einem Kuchen ist? Ja. Definitiv ja.",
	"source": "season",
	"sourceDescription": "Saison",
	"howToGet": "Belohnung f\u00fcr alle Spieler, die im April 2015 im gewerteten Modus Rang 20 erreicht haben.",
	"enabled": true,
	"img": "http://wow.zamimg.com/images/hearthstone/backs/original/Card_Back_Cupcake.png",
	"imgAnimated": "http://wow.zamimg.com/images/hearthstone/backs/animated/Card_Back_Cupcake.gif",
	"sortCategory": "5",
	"sortOrder": "0",
	"locale": "deDE"
},
{
	"cardBackId": "23",
	"name": "Ninjas!",
	"description": "Stille Spione mit Stil und Shuriken. So viel besser als Piraten!",
	"source": "season",
	"sourceDescription": "Saison",
	"howToGet": "Belohnung f\u00fcr alle Spieler, die im Mai 2015 im gewerteten Modus Rang 20 erreicht haben.",
	"enabled": true,
	"img": "http://wow.zamimg.com/images/hearthstone/backs/original/Card_Back_Ninja.png",
	"imgAnimated": "http://wow.zamimg.com/images/hearthstone/backs/animated/Card_Back_Ninja.gif",
	"sortCategory": "5",
	"sortOrder": "0",
	"locale": "deDE"
},
{
	"cardBackId": "24",
	"name": "Heroes of the Storm",
	"description": "Soeben aus dem Nexus f\u00fcr Euch angekommen. Ihr solltet wahrscheinlich auf die drehenden spitzen Dinger achtgeben.",
	"source": "achieve",
	"sourceDescription": "Promo",
	"howToGet": "Belohnung f\u00fcr Spieler, die im Blizzard-Spiel \u201eHeroes of the Storm\u201c Spielerstufe 12 erreicht haben.",
	"enabled": true,
	"img": "http://wow.zamimg.com/images/hearthstone/backs/original/Card_Back_HotS.png",
	"imgAnimated": "http://wow.zamimg.com/images/hearthstone/backs/animated/Card_Back_HotS.gif",
	"sortCategory": "8",
	"sortOrder": "1",
	"locale": "deDE"
},
{
	"cardBackId": "25",
	"name": "Alleria",
	"description": "Wenn sie Euch einen Apfel vom Kopf schie\u00dfen will, m\u00fcsst Ihr Euch keine Sorgen machen. Es sei denn, Ihr seid ein Orc.",
	"source": "fixed_reward",
	"sourceDescription": "Held",
	"howToGet": "Belohnung f\u00fcr Spieler, die die Heldin Alleria Windl\u00e4ufer erworben haben.",
	"enabled": true,
	"img": "http://wow.zamimg.com/images/hearthstone/backs/original/Card_Back_Alleria.png",
	"imgAnimated": "http://wow.zamimg.com/images/hearthstone/backs/animated/Card_Back_Alleria.gif",
	"sortCategory": "4",
	"sortOrder": "3",
	"locale": "deDE"
},
{
	"cardBackId": "26",
	"name": "Magni",
	"description": "Magni ist ein facettenreicher und brillanter Anf\u00fchrer. Wer wei\u00df, was die Zukunft alles f\u00fcr ihn bereith\u00e4lt ...",
	"source": "fixed_reward",
	"sourceDescription": "Held",
	"howToGet": "Belohnung f\u00fcr Spieler, die den Helden Magni Bronzebart erworben haben.",
	"enabled": true,
	"img": "http://wow.zamimg.com/images/hearthstone/backs/original/Card_Back_Magni.png",
	"imgAnimated": "http://wow.zamimg.com/images/hearthstone/backs/animated/Card_Back_Magni.gif",
	"sortCategory": "4",
	"sortOrder": "2",
	"locale": "deDE"
},
{
	"cardBackId": "27",
	"name": "Medivh",
	"description": "Er hat eine Vorliebe f\u00fcr Kr\u00e4hen und Raben. Vielleicht \u00fcbertreibt er etwas.",
	"source": "fixed_reward",
	"sourceDescription": "Held",
	"howToGet": "Belohnung f\u00fcr Spieler, die den Helden Medivh erworben haben.",
	"enabled": true,
	"img": "http://wow.zamimg.com/images/hearthstone/backs/original/Card_Back_Medivh.png",
	"imgAnimated": "http://wow.zamimg.com/images/hearthstone/backs/animated/Card_Back_Medivh.gif",
	"sortCategory": "4",
	"sortOrder": "1",
	"locale": "deDE"
},
{
	"cardBackId": "28",
	"name": "Darnassus",
	"description": "Die Hauptstadt der Nachtelfen und Geburtsort des weltber\u00fchmten darnassischen Kimchikuchens!",
	"source": "season",
	"howToGet": "Belohnung f\u00fcr alle Spieler, die im Juni 2015 im gewerteten Modus Rang 20 erreicht haben.",
	"enabled": true,
	"img": "http://wow.zamimg.com/images/hearthstone/backs/original/Card_Back_Druid.png",
	"imgAnimated": "http://wow.zamimg.com/images/hearthstone/backs/animated/Card_Back_Druid.gif",
	"sortCategory": "5",
	"sortOrder": "0",
	"locale": "deDE"
},
{
	"cardBackId": "29",
	"name": "GALAXY-Geschenke",
	"description": "Galaktische Geschenke! Dieser Kartenr\u00fccken ist wirklich nicht von dieser Welt.",
	"source": "fixed_reward",
	"howToGet": "Belohnung f\u00fcr Spieler, die an der Samsung-Promo \u201eGALAXY-Geschenke\u201c teilgenommen haben.",
	"enabled": true,
	"img": "http://wow.zamimg.com/images/hearthstone/backs/original/Card_Back_Samsung.png",
	"imgAnimated": "http://wow.zamimg.com/images/hearthstone/backs/animated/Card_Back_Samsung.gif",
	"sortCategory": "9",
	"sortOrder": "1",
	"locale": "deDE"
},
{
	"cardBackId": "30",
	"name": "Dunkelspeere",
	"description": "Vol'jins Stamm, die Dunkelspeertrolle, praktizieren keinen Kannibalismus mehr. Offiziell.",
	"source": "season",
	"howToGet": "Belohnung f\u00fcr alle Spieler, die im Juli 2015 im gewerteten Modus Rang 20 erreicht haben.",
	"enabled": true,
	"img": "http://wow.zamimg.com/images/hearthstone/backs/original/Card_Back_Troll.png",
	"imgAnimated": "http://wow.zamimg.com/images/hearthstone/backs/animated/Card_Back_Troll.gif",
	"sortCategory": "5",
	"sortOrder": "0",
	"locale": "deDE"
},
{
	"cardBackId": "31",
	"name": "Das Gro\u00dfe Turnier",
	"description": "Nach dem Sieg \u00fcber den Lichk\u00f6nig wurde ordentlich gefeiert, danach machten sich die meisten auf den Heimweg. Die Verbliebenen f\u00fchrten das Turnier mit einem neuen Ziel weiter: Spa\u00df haben!",
	"source": "fixed_reward",
	"howToGet": "Belohnung f\u00fcr Spieler, die Kartenpackungen f\u00fcr das Gro\u00dfe Turnier im Vorverkauf erworben haben.",
	"enabled": true,
	"img": "http://wow.zamimg.com/images/hearthstone/backs/original/Card_Back_TGT.png",
	"imgAnimated": "http://wow.zamimg.com/images/hearthstone/backs/animated/Card_Back_TGT.gif",
	"sortCategory": "10",
	"sortOrder": "2",
	"locale": "deDE"
},
{
	"cardBackId": "32",
	"name": "Turniergel\u00e4nde",
	"description": "Wo man auch hinsieht, trainieren Ritter f\u00fcr das Gro\u00dfe Turnier. Arme Zielattrappen \u2013 so viele sind dem Streben nach Ruhm zum Opfer gefallen ...",
	"source": "season",
	"howToGet": "Belohnung f\u00fcr alle Spieler, die im August 2015 im gewerteten Modus Rang 20 erreicht haben.",
	"enabled": true,
	"img": "http://wow.zamimg.com/images/hearthstone/backs/original/Card_Back_TGT_Season.png",
	"imgAnimated": "http://wow.zamimg.com/images/hearthstone/backs/animated/Card_Back_TGT_Season.gif",
	"sortCategory": "5",
	"sortOrder": "0",
	"locale": "deDE"
},
{
	"cardBackId": "33",
	"name": "Kraftkern",
	"description": "Dieser Kartenr\u00fccken strotzt nur so vor Energie ... die von Euch auszugehen scheint!",
	"source": "achieve",
	"howToGet": "Belohnung f\u00fcr die Teilnahme an ausgew\u00e4hlten eSports-Events.",
	"enabled": true,
	"img": "http://wow.zamimg.com/images/hearthstone/backs/original/Card_Back_Esports.png",
	"imgAnimated": "http://wow.zamimg.com/images/hearthstone/backs/animated/Card_Back_Esports.gif",
	"sortCategory": "12",
	"sortOrder": "2",
	"locale": "deDE"
},
{
	"cardBackId": "34",
	"name": "Die Exodar",
	"description": "Die Draenei-Hauptstadt ist eigentlich ein Raumschiff, das nach einem Abstecher im Wirbelnden Nether auf Azeroth abst\u00fcrzte. Trotz Velens Bem\u00fchungen lockt die Region nur wenige Touristen an, was am isolierten Standort liegt (vielleicht auch an den muti",
	"source": "season",
	"howToGet": "Belohnung f\u00fcr alle Spieler, die im September 2015 im gewerteten Modus Rang 20 erreicht haben.",
	"enabled": true,
	"img": "http://wow.zamimg.com/images/hearthstone/backs/original/Card_Back_Draenei.png",
	"imgAnimated": "http://wow.zamimg.com/images/hearthstone/backs/animated/Card_Back_Draenei.gif",
	"sortCategory": "5",
	"sortOrder": "0",
	"locale": "deDE"
}]